requests_credssp/__init__.py
requests_credssp/credssp.py
requests_credssp/exceptions.py
requests_credssp-2.0.0.dist-info/LICENSE
requests_credssp-2.0.0.dist-info/METADATA
requests_credssp-2.0.0.dist-info/WHEEL
requests_credssp-2.0.0.dist-info/top_level.txt
requests_credssp-2.0.0.dist-info/RECORD
