Metadata-Version: 2.1
Name: requests-credssp
Version: 2.0.0
Summary: HTTPS CredSSP authentication with the requests library.
Home-page: https://github.com/jborean93/requests-credssp
Author: Jordan Borean
Author-email: jborean93@gmail.com
License: MIT
Keywords: authentication auth microsoft credssp winrm
Platform: UNKNOWN
Classifier: Development Status :: 4 - Beta
Classifier: License :: OSI Approved :: BSD License
Classifier: Programming Language :: Python :: 3
Classifier: Programming Language :: Python :: 3.6
Classifier: Programming Language :: Python :: 3.7
Classifier: Programming Language :: Python :: 3.8
Classifier: Programming Language :: Python :: 3.9
Classifier: Programming Language :: Python :: 3.10
Requires-Python: >=3.6
Provides-Extra: kerberos
License-File: LICENSE
